{
  "tables": [
    {
      "id": "2077a3dc4596",
      "name": "core.package",
      "x": -539.9189408459036,
      "y": 48.81843437025739,
      "fields": [
        {
          "id": "43f96212aca6",
          "name": "id",
          "type": "BIGINT",
          "default": "",
          "check": "",
          "primary": true,
          "unique": true,
          "notNull": false,
          "increment": true,
          "comment": ""
        },
        {
          "id": "bfc469cf32e4",
          "name": "technical_name",
          "type": "TEXT",
          "default": "",
          "check": "",
          "primary": false,
          "unique": false,
          "notNull": true,
          "increment": false,
          "comment": ""
        },
        {
          "id": "d7d3771d2c66",
          "name": "display_name",
          "type": "TEXT",
          "default": "",
          "check": "",
          "primary": false,
          "unique": false,
          "notNull": true,
          "increment": false,
          "comment": ""
        },
        {
          "id": "8d6e08b08f09",
          "name": "status",
          "type": "TEXT",
          "default": "'active'",
          "check": "",
          "primary": false,
          "unique": false,
          "notNull": true,
          "increment": false,
          "comment": ""
        },
        {
          "id": "af436e59ce54",
          "name": "created_at_utc",
          "type": "TIMESTAMPTZ",
          "default": "now()",
          "check": "",
          "primary": false,
          "unique": false,
          "notNull": true,
          "increment": false,
          "comment": ""
        }
      ],
      "comment": "",
      "indices": [],
      "color": "#1a6b8a",
      "locked": false
    },
    {
      "id": "63d49611d493",
      "name": "core.entity_kind",
      "x": 6.4043873966943465,
      "y": 12.048276094954275,
      "fields": [
        {
          "id": "fcec06e18082",
          "name": "id",
          "type": "BIGINT",
          "default": "",
          "check": "",
          "primary": true,
          "unique": true,
          "notNull": false,
          "increment": true,
          "comment": ""
        },
        {
          "id": "eab8e4558f4c",
          "name": "package_id",
          "type": "BIGINT",
          "default": "",
          "check": "",
          "primary": false,
          "unique": false,
          "notNull": true,
          "increment": false,
          "comment": ""
        },
        {
          "id": "bb6ae5e26ad4",
          "name": "technical_name",
          "type": "TEXT",
          "default": "",
          "check": "",
          "primary": false,
          "unique": false,
          "notNull": true,
          "increment": false,
          "comment": ""
        },
        {
          "id": "0ca81b7a01b0",
          "name": "display_name",
          "type": "TEXT",
          "default": "",
          "check": "",
          "primary": false,
          "unique": false,
          "notNull": true,
          "increment": false,
          "comment": ""
        },
        {
          "id": "3e565e24f619",
          "name": "segment_allowed_flag",
          "type": "BOOLEAN",
          "default": "true",
          "check": "",
          "primary": false,
          "unique": false,
          "notNull": true,
          "increment": false,
          "comment": ""
        },
        {
          "id": "87d545eb8669",
          "name": "created_at_utc",
          "type": "TIMESTAMPTZ",
          "default": "now()",
          "check": "",
          "primary": false,
          "unique": false,
          "notNull": true,
          "increment": false,
          "comment": ""
        }
      ],
      "comment": "",
      "indices": [],
      "color": "#1a6b8a",
      "locked": false
    },
    {
      "id": "125211c0e9d8",
      "name": "core.location_node",
      "x": 842.1913584159051,
      "y": 656.9638533837804,
      "fields": [
        {
          "id": "62495d8bd079",
          "name": "id",
          "type": "BIGINT",
          "default": "",
          "check": "",
          "primary": true,
          "unique": true,
          "notNull": false,
          "increment": true,
          "comment": ""
        },
        {
          "id": "fafb8f66c070",
          "name": "parent_location_node_id",
          "type": "BIGINT",
          "default": "",
          "check": "",
          "primary": false,
          "unique": false,
          "notNull": false,
          "increment": false,
          "comment": ""
        },
        {
          "id": "88cf6c1c40cb",
          "name": "location_kind",
          "type": "TEXT",
          "default": "",
          "check": "",
          "primary": false,
          "unique": false,
          "notNull": true,
          "increment": false,
          "comment": ""
        },
        {
          "id": "e56e4587c5cc",
          "name": "technical_name",
          "type": "TEXT",
          "default": "",
          "check": "",
          "primary": false,
          "unique": false,
          "notNull": true,
          "increment": false,
          "comment": ""
        },
        {
          "id": "1f5a3b2914d4",
          "name": "display_name",
          "type": "TEXT",
          "default": "",
          "check": "",
          "primary": false,
          "unique": false,
          "notNull": true,
          "increment": false,
          "comment": ""
        },
        {
          "id": "3b255ad6825a",
          "name": "country_code",
          "type": "CHAR(2)",
          "default": "",
          "check": "",
          "primary": false,
          "unique": false,
          "notNull": false,
          "increment": false,
          "comment": ""
        },
        {
          "id": "330b3af906a2",
          "name": "timezone_name",
          "type": "TEXT",
          "default": "",
          "check": "",
          "primary": false,
          "unique": false,
          "notNull": false,
          "increment": false,
          "comment": ""
        },
        {
          "id": "2e624002a990",
          "name": "valid_from",
          "type": "DATE",
          "default": "",
          "check": "",
          "primary": false,
          "unique": false,
          "notNull": true,
          "increment": false,
          "comment": ""
        },
        {
          "id": "ad394ce117ea",
          "name": "valid_to",
          "type": "DATE",
          "default": "",
          "check": "",
          "primary": false,
          "unique": false,
          "notNull": false,
          "increment": false,
          "comment": ""
        },
        {
          "id": "5e2d7fd680ba",
          "name": "created_at_utc",
          "type": "TIMESTAMPTZ",
          "default": "now()",
          "check": "",
          "primary": false,
          "unique": false,
          "notNull": true,
          "increment": false,
          "comment": ""
        }
      ],
      "comment": "",
      "indices": [],
      "color": "#1a6b8a",
      "locked": false
    },
    {
      "id": "0f9b42fb0c13",
      "name": "core.item",
      "x": 1302.5832981814058,
      "y": -23.908695987722126,
      "fields": [
        {
          "id": "45bf069cf3c1",
          "name": "id",
          "type": "BIGINT",
          "default": "",
          "check": "",
          "primary": true,
          "unique": true,
          "notNull": false,
          "increment": true,
          "comment": ""
        },
        {
          "id": "24d18c0f8fb3",
          "name": "entity_kind_id",
          "type": "BIGINT",
          "default": "",
          "check": "",
          "primary": false,
          "unique": false,
          "notNull": true,
          "increment": false,
          "comment": ""
        },
        {
          "id": "466f744611c9",
          "name": "location_node_id",
          "type": "BIGINT",
          "default": "",
          "check": "",
          "primary": false,
          "unique": false,
          "notNull": true,
          "increment": false,
          "comment": ""
        },
        {
          "id": "b4ec9ac6bcf0",
          "name": "code",
          "type": "TEXT",
          "default": "",
          "check": "",
          "primary": false,
          "unique": false,
          "notNull": true,
          "increment": false,
          "comment": ""
        },
        {
          "id": "44db3ca675e6",
          "name": "start_date",
          "type": "DATE",
          "default": "",
          "check": "",
          "primary": false,
          "unique": false,
          "notNull": true,
          "increment": false,
          "comment": ""
        },
        {
          "id": "c5e3099190f8",
          "name": "end_date",
          "type": "DATE",
          "default": "",
          "check": "",
          "primary": false,
          "unique": false,
          "notNull": false,
          "increment": false,
          "comment": ""
        },
        {
          "id": "ff5a020c1957",
          "name": "status",
          "type": "TEXT",
          "default": "'active'",
          "check": "",
          "primary": false,
          "unique": false,
          "notNull": true,
          "increment": false,
          "comment": ""
        },
        {
          "id": "235812fa9f40",
          "name": "created_at_utc",
          "type": "TIMESTAMPTZ",
          "default": "now()",
          "check": "",
          "primary": false,
          "unique": false,
          "notNull": true,
          "increment": false,
          "comment": ""
        }
      ],
      "comment": "",
      "indices": [],
      "color": "#1a6b8a",
      "locked": false
    },
    {
      "id": "ec6e286ec1e3",
      "name": "core.segment",
      "x": 1954.6699501920605,
      "y": 292.24693682336647,
      "fields": [
        {
          "id": "ae5314c6a377",
          "name": "id",
          "type": "BIGINT",
          "default": "",
          "check": "",
          "primary": true,
          "unique": true,
          "notNull": false,
          "increment": true,
          "comment": ""
        },
        {
          "id": "29ed96142b36",
          "name": "item_id",
          "type": "BIGINT",
          "default": "",
          "check": "",
          "primary": false,
          "unique": false,
          "notNull": true,
          "increment": false,
          "comment": ""
        },
        {
          "id": "593d350e8947",
          "name": "location_node_id",
          "type": "BIGINT",
          "default": "",
          "check": "",
          "primary": false,
          "unique": false,
          "notNull": true,
          "increment": false,
          "comment": ""
        },
        {
          "id": "60924bc6681e",
          "name": "parent_segment_id",
          "type": "BIGINT",
          "default": "",
          "check": "",
          "primary": false,
          "unique": false,
          "notNull": false,
          "increment": false,
          "comment": ""
        },
        {
          "id": "d67fa4c0897a",
          "name": "code",
          "type": "TEXT",
          "default": "",
          "check": "",
          "primary": false,
          "unique": false,
          "notNull": true,
          "increment": false,
          "comment": ""
        },
        {
          "id": "75037fdeca62",
          "name": "start_date",
          "type": "DATE",
          "default": "",
          "check": "",
          "primary": false,
          "unique": false,
          "notNull": true,
          "increment": false,
          "comment": ""
        },
        {
          "id": "61f5fa7d1c44",
          "name": "end_date",
          "type": "DATE",
          "default": "",
          "check": "",
          "primary": false,
          "unique": false,
          "notNull": false,
          "increment": false,
          "comment": ""
        },
        {
          "id": "8782ca381cc4",
          "name": "status",
          "type": "TEXT",
          "default": "'active'",
          "check": "",
          "primary": false,
          "unique": false,
          "notNull": true,
          "increment": false,
          "comment": ""
        },
        {
          "id": "fd8f91899530",
          "name": "split_reason",
          "type": "TEXT",
          "default": "",
          "check": "",
          "primary": false,
          "unique": false,
          "notNull": false,
          "increment": false,
          "comment": ""
        },
        {
          "id": "6eb6b152dd75",
          "name": "created_at_utc",
          "type": "TIMESTAMPTZ",
          "default": "now()",
          "check": "",
          "primary": false,
          "unique": false,
          "notNull": true,
          "increment": false,
          "comment": ""
        }
      ],
      "comment": "",
      "indices": [],
      "color": "#1a6b8a",
      "locked": false
    },
    {
      "id": "796acc97f2ea",
      "name": "core.event",
      "x": 85.38008760004766,
      "y": 382.50117595924036,
      "fields": [
        {
          "id": "a5c40af57d80",
          "name": "id",
          "type": "BIGINT",
          "default": "",
          "check": "",
          "primary": true,
          "unique": true,
          "notNull": false,
          "increment": true,
          "comment": ""
        },
        {
          "id": "9410077f84d6",
          "name": "package_id",
          "type": "BIGINT",
          "default": "",
          "check": "",
          "primary": false,
          "unique": false,
          "notNull": true,
          "increment": false,
          "comment": ""
        },
        {
          "id": "767369a23cf0",
          "name": "item_id",
          "type": "BIGINT",
          "default": "",
          "check": "",
          "primary": false,
          "unique": false,
          "notNull": false,
          "increment": false,
          "comment": ""
        },
        {
          "id": "e8c84bb6ba06",
          "name": "segment_id",
          "type": "BIGINT",
          "default": "",
          "check": "",
          "primary": false,
          "unique": false,
          "notNull": false,
          "increment": false,
          "comment": ""
        },
        {
          "id": "84c279d51788",
          "name": "location_node_id",
          "type": "BIGINT",
          "default": "",
          "check": "",
          "primary": false,
          "unique": false,
          "notNull": false,
          "increment": false,
          "comment": ""
        },
        {
          "id": "60fd5b55e8a7",
          "name": "event_type",
          "type": "TEXT",
          "default": "",
          "check": "",
          "primary": false,
          "unique": false,
          "notNull": true,
          "increment": false,
          "comment": ""
        },
        {
          "id": "6236e693969d",
          "name": "business_date",
          "type": "DATE",
          "default": "",
          "check": "",
          "primary": false,
          "unique": false,
          "notNull": true,
          "increment": false,
          "comment": ""
        },
        {
          "id": "a7d73cabe85e",
          "name": "occurred_at_utc",
          "type": "TIMESTAMPTZ",
          "default": "",
          "check": "",
          "primary": false,
          "unique": false,
          "notNull": true,
          "increment": false,
          "comment": ""
        },
        {
          "id": "f1210f2ad259",
          "name": "effective_from",
          "type": "DATE",
          "default": "",
          "check": "",
          "primary": false,
          "unique": false,
          "notNull": true,
          "increment": false,
          "comment": ""
        },
        {
          "id": "4426f7e4e653",
          "name": "effective_to",
          "type": "DATE",
          "default": "",
          "check": "",
          "primary": false,
          "unique": false,
          "notNull": false,
          "increment": false,
          "comment": ""
        },
        {
          "id": "89e86a61466f",
          "name": "source_system",
          "type": "TEXT",
          "default": "",
          "check": "",
          "primary": false,
          "unique": false,
          "notNull": false,
          "increment": false,
          "comment": ""
        },
        {
          "id": "da3487f2fd58",
          "name": "payload_jsonb",
          "type": "JSONB",
          "default": "",
          "check": "",
          "primary": false,
          "unique": false,
          "notNull": false,
          "increment": false,
          "comment": ""
        },
        {
          "id": "f4a619aa897a",
          "name": "created_at_utc",
          "type": "TIMESTAMPTZ",
          "default": "now()",
          "check": "",
          "primary": false,
          "unique": false,
          "notNull": true,
          "increment": false,
          "comment": ""
        }
      ],
      "comment": "",
      "indices": [],
      "color": "#1a6b8a",
      "locked": false
    },
    {
      "id": "afe9774dbb38",
      "name": "core.scenario",
      "x": 1934.253273885268,
      "y": 1082.338641579658,
      "fields": [
        {
          "id": "bbef6c4f9dc3",
          "name": "id",
          "type": "BIGINT",
          "default": "",
          "check": "",
          "primary": true,
          "unique": true,
          "notNull": false,
          "increment": true,
          "comment": ""
        },
        {
          "id": "a94645f6b762",
          "name": "technical_name",
          "type": "TEXT",
          "default": "",
          "check": "",
          "primary": false,
          "unique": false,
          "notNull": true,
          "increment": false,
          "comment": ""
        },
        {
          "id": "66181a774fb0",
          "name": "scenario_kind",
          "type": "TEXT",
          "default": "",
          "check": "",
          "primary": false,
          "unique": false,
          "notNull": true,
          "increment": false,
          "comment": ""
        },
        {
          "id": "d62f9685dabf",
          "name": "parent_scenario_id",
          "type": "BIGINT",
          "default": "",
          "check": "",
          "primary": false,
          "unique": false,
          "notNull": false,
          "increment": false,
          "comment": ""
        },
        {
          "id": "ed2867577427",
          "name": "is_official_flag",
          "type": "BOOLEAN",
          "default": "false",
          "check": "",
          "primary": false,
          "unique": false,
          "notNull": true,
          "increment": false,
          "comment": ""
        },
        {
          "id": "f5666fa645d4",
          "name": "created_at_utc",
          "type": "TIMESTAMPTZ",
          "default": "now()",
          "check": "",
          "primary": false,
          "unique": false,
          "notNull": true,
          "increment": false,
          "comment": ""
        }
      ],
      "comment": "",
      "indices": [],
      "color": "#1a6b8a",
      "locked": false
    },
    {
      "id": "ddf9eb81b96b",
      "name": "core.calc_version",
      "x": 1997.0207360704949,
      "y": 1450.0166537184107,
      "fields": [
        {
          "id": "335702703e9f",
          "name": "id",
          "type": "BIGINT",
          "default": "",
          "check": "",
          "primary": true,
          "unique": true,
          "notNull": false,
          "increment": true,
          "comment": ""
        },
        {
          "id": "468629b7faa4",
          "name": "engine_version",
          "type": "TEXT",
          "default": "",
          "check": "",
          "primary": false,
          "unique": false,
          "notNull": true,
          "increment": false,
          "comment": ""
        },
        {
          "id": "fe238884de0b",
          "name": "rule_bundle_version",
          "type": "TEXT",
          "default": "",
          "check": "",
          "primary": false,
          "unique": false,
          "notNull": true,
          "increment": false,
          "comment": ""
        },
        {
          "id": "ad7c897961c4",
          "name": "created_at_utc",
          "type": "TIMESTAMPTZ",
          "default": "now()",
          "check": "",
          "primary": false,
          "unique": false,
          "notNull": true,
          "increment": false,
          "comment": ""
        }
      ],
      "comment": "",
      "indices": [],
      "color": "#1a6b8a",
      "locked": false
    },
    {
      "id": "76898c7db092",
      "name": "meta.attribute",
      "x": -52.93826453378824,
      "y": 1046.2408722361995,
      "fields": [
        {
          "id": "3181e2ff3c43",
          "name": "id",
          "type": "BIGINT",
          "default": "",
          "check": "",
          "primary": true,
          "unique": true,
          "notNull": false,
          "increment": true,
          "comment": ""
        },
        {
          "id": "25aacad20881",
          "name": "package_id",
          "type": "BIGINT",
          "default": "",
          "check": "",
          "primary": false,
          "unique": false,
          "notNull": true,
          "increment": false,
          "comment": ""
        },
        {
          "id": "56aba6b91eff",
          "name": "technical_name",
          "type": "TEXT",
          "default": "",
          "check": "",
          "primary": false,
          "unique": false,
          "notNull": true,
          "increment": false,
          "comment": ""
        },
        {
          "id": "2cfa1c42298b",
          "name": "display_name",
          "type": "TEXT",
          "default": "",
          "check": "",
          "primary": false,
          "unique": false,
          "notNull": true,
          "increment": false,
          "comment": ""
        },
        {
          "id": "2340e8ca329b",
          "name": "value_type",
          "type": "TEXT",
          "default": "",
          "check": "",
          "primary": false,
          "unique": false,
          "notNull": true,
          "increment": false,
          "comment": ""
        },
        {
          "id": "aadfee57eca4",
          "name": "business_role",
          "type": "TEXT",
          "default": "",
          "check": "",
          "primary": false,
          "unique": false,
          "notNull": true,
          "increment": false,
          "comment": ""
        },
        {
          "id": "7b42ceb1a6a4",
          "name": "grain_kind",
          "type": "TEXT",
          "default": "",
          "check": "",
          "primary": false,
          "unique": false,
          "notNull": true,
          "increment": false,
          "comment": ""
        },
        {
          "id": "93a6b4d85223",
          "name": "aggregation_rule",
          "type": "TEXT",
          "default": "",
          "check": "",
          "primary": false,
          "unique": false,
          "notNull": true,
          "increment": false,
          "comment": ""
        },
        {
          "id": "64cc693b93db",
          "name": "unit_code",
          "type": "TEXT",
          "default": "",
          "check": "",
          "primary": false,
          "unique": false,
          "notNull": false,
          "increment": false,
          "comment": ""
        },
        {
          "id": "daaae2ed9d47",
          "name": "precision_scale",
          "type": "INTEGER",
          "default": "",
          "check": "",
          "primary": false,
          "unique": false,
          "notNull": false,
          "increment": false,
          "comment": ""
        },
        {
          "id": "a475080318ca",
          "name": "panel_visible_flag",
          "type": "BOOLEAN",
          "default": "true",
          "check": "",
          "primary": false,
          "unique": false,
          "notNull": true,
          "increment": false,
          "comment": ""
        },
        {
          "id": "3bcae421d5fc",
          "name": "audit_required_flag",
          "type": "BOOLEAN",
          "default": "true",
          "check": "",
          "primary": false,
          "unique": false,
          "notNull": true,
          "increment": false,
          "comment": ""
        },
        {
          "id": "60671fcb604c",
          "name": "created_at_utc",
          "type": "TIMESTAMPTZ",
          "default": "now()",
          "check": "",
          "primary": false,
          "unique": false,
          "notNull": true,
          "increment": false,
          "comment": ""
        }
      ],
      "comment": "",
      "indices": [],
      "color": "#c4c410",
      "locked": false
    },
    {
      "id": "05ea7bc82a14",
      "name": "fact.daily_measure_fact",
      "x": 1403.0481376412465,
      "y": 865.5815420330656,
      "fields": [
        {
          "id": "e8db65ed3130",
          "name": "id",
          "type": "BIGINT",
          "default": "",
          "check": "",
          "primary": true,
          "unique": true,
          "notNull": false,
          "increment": true,
          "comment": ""
        },
        {
          "id": "b5f655a5f865",
          "name": "fact_date",
          "type": "DATE",
          "default": "",
          "check": "",
          "primary": false,
          "unique": false,
          "notNull": true,
          "increment": false,
          "comment": ""
        },
        {
          "id": "73d25a8d37d2",
          "name": "item_id",
          "type": "BIGINT",
          "default": "",
          "check": "",
          "primary": false,
          "unique": false,
          "notNull": true,
          "increment": false,
          "comment": ""
        },
        {
          "id": "8ed8e57782a2",
          "name": "segment_id",
          "type": "BIGINT",
          "default": "",
          "check": "",
          "primary": false,
          "unique": false,
          "notNull": true,
          "increment": false,
          "comment": ""
        },
        {
          "id": "2a0280450d52",
          "name": "location_node_id",
          "type": "BIGINT",
          "default": "",
          "check": "",
          "primary": false,
          "unique": false,
          "notNull": true,
          "increment": false,
          "comment": ""
        },
        {
          "id": "a8f75c117533",
          "name": "attribute_id",
          "type": "BIGINT",
          "default": "",
          "check": "",
          "primary": false,
          "unique": false,
          "notNull": true,
          "increment": false,
          "comment": ""
        },
        {
          "id": "fa7c8f774f6a",
          "name": "scenario_id",
          "type": "BIGINT",
          "default": "",
          "check": "",
          "primary": false,
          "unique": false,
          "notNull": true,
          "increment": false,
          "comment": ""
        },
        {
          "id": "19cc4a617ba0",
          "name": "calc_version_id",
          "type": "BIGINT",
          "default": "",
          "check": "",
          "primary": false,
          "unique": false,
          "notNull": true,
          "increment": false,
          "comment": ""
        },
        {
          "id": "42fed9dca89f",
          "name": "measure_value",
          "type": "NUMERIC(18, 6)",
          "default": "",
          "check": "",
          "primary": false,
          "unique": false,
          "notNull": true,
          "increment": false,
          "comment": ""
        },
        {
          "id": "9815776d3345",
          "name": "unit_code",
          "type": "TEXT",
          "default": "",
          "check": "",
          "primary": false,
          "unique": false,
          "notNull": true,
          "increment": false,
          "comment": ""
        },
        {
          "id": "760a92a644df",
          "name": "created_at_utc",
          "type": "TIMESTAMPTZ",
          "default": "now()",
          "check": "",
          "primary": false,
          "unique": false,
          "notNull": true,
          "increment": false,
          "comment": ""
        }
      ],
      "comment": "",
      "indices": [],
      "color": "#6270f0",
      "locked": false
    }
  ],
  "relationships": [
    {
      "id": "135dd48cc841",
      "name": "fk_core.entity_kind_package_id_core.package",
      "startTableId": "63d49611d493",
      "startFieldId": "eab8e4558f4c",
      "endTableId": "2077a3dc4596",
      "endFieldId": "43f96212aca6",
      "cardinality": "many_to_one",
      "updateConstraint": "No action",
      "deleteConstraint": "No action"
    },
    {
      "id": "9d930d41a339",
      "name": "fk_core.location_node_parent_location_node_id_core.location_node",
      "startTableId": "125211c0e9d8",
      "startFieldId": "fafb8f66c070",
      "endTableId": "125211c0e9d8",
      "endFieldId": "62495d8bd079",
      "cardinality": "many_to_one",
      "updateConstraint": "No action",
      "deleteConstraint": "No action"
    },
    {
      "id": "f3078db8fd4d",
      "name": "fk_core.item_entity_kind_id_core.entity_kind",
      "startTableId": "0f9b42fb0c13",
      "startFieldId": "24d18c0f8fb3",
      "endTableId": "63d49611d493",
      "endFieldId": "fcec06e18082",
      "cardinality": "many_to_one",
      "updateConstraint": "No action",
      "deleteConstraint": "No action"
    },
    {
      "id": "cd906ad898c6",
      "name": "fk_core.item_location_node_id_core.location_node",
      "startTableId": "0f9b42fb0c13",
      "startFieldId": "466f744611c9",
      "endTableId": "125211c0e9d8",
      "endFieldId": "62495d8bd079",
      "cardinality": "many_to_one",
      "updateConstraint": "No action",
      "deleteConstraint": "No action"
    },
    {
      "id": "2ba788396a15",
      "name": "fk_core.segment_item_id_core.item",
      "startTableId": "ec6e286ec1e3",
      "startFieldId": "29ed96142b36",
      "endTableId": "0f9b42fb0c13",
      "endFieldId": "45bf069cf3c1",
      "cardinality": "many_to_one",
      "updateConstraint": "No action",
      "deleteConstraint": "No action"
    },
    {
      "id": "1283a35fce62",
      "name": "fk_core.segment_location_node_id_core.location_node",
      "startTableId": "ec6e286ec1e3",
      "startFieldId": "593d350e8947",
      "endTableId": "125211c0e9d8",
      "endFieldId": "62495d8bd079",
      "cardinality": "many_to_one",
      "updateConstraint": "No action",
      "deleteConstraint": "No action"
    },
    {
      "id": "20df78670d14",
      "name": "fk_core.segment_parent_segment_id_core.segment",
      "startTableId": "ec6e286ec1e3",
      "startFieldId": "60924bc6681e",
      "endTableId": "ec6e286ec1e3",
      "endFieldId": "ae5314c6a377",
      "cardinality": "many_to_one",
      "updateConstraint": "No action",
      "deleteConstraint": "No action"
    },
    {
      "id": "264976d3720c",
      "name": "fk_core.event_package_id_core.package",
      "startTableId": "796acc97f2ea",
      "startFieldId": "9410077f84d6",
      "endTableId": "2077a3dc4596",
      "endFieldId": "43f96212aca6",
      "cardinality": "many_to_one",
      "updateConstraint": "No action",
      "deleteConstraint": "No action"
    },
    {
      "id": "5ddb32bd2253",
      "name": "fk_core.event_item_id_core.item",
      "startTableId": "796acc97f2ea",
      "startFieldId": "767369a23cf0",
      "endTableId": "0f9b42fb0c13",
      "endFieldId": "45bf069cf3c1",
      "cardinality": "many_to_one",
      "updateConstraint": "No action",
      "deleteConstraint": "No action"
    },
    {
      "id": "eea8a519ac07",
      "name": "fk_core.event_location_node_id_core.location_node",
      "startTableId": "796acc97f2ea",
      "startFieldId": "84c279d51788",
      "endTableId": "125211c0e9d8",
      "endFieldId": "62495d8bd079",
      "cardinality": "many_to_one",
      "updateConstraint": "No action",
      "deleteConstraint": "No action"
    },
    {
      "id": "48fa3aa56ef6",
      "name": "fk_core.event_segment_id_core.segment",
      "startTableId": "796acc97f2ea",
      "startFieldId": "e8c84bb6ba06",
      "endTableId": "ec6e286ec1e3",
      "endFieldId": "ae5314c6a377",
      "cardinality": "many_to_one",
      "updateConstraint": "No action",
      "deleteConstraint": "No action"
    },
    {
      "id": "a1f4cfeb1678",
      "name": "fk_core.event_item_id_core.segment",
      "startTableId": "796acc97f2ea",
      "startFieldId": "767369a23cf0",
      "endTableId": "ec6e286ec1e3",
      "endFieldId": "29ed96142b36",
      "cardinality": "many_to_one",
      "updateConstraint": "No action",
      "deleteConstraint": "No action"
    },
    {
      "id": "a0f8b2c7a296",
      "name": "fk_core.scenario_parent_scenario_id_core.scenario",
      "startTableId": "afe9774dbb38",
      "startFieldId": "d62f9685dabf",
      "endTableId": "afe9774dbb38",
      "endFieldId": "bbef6c4f9dc3",
      "cardinality": "many_to_one",
      "updateConstraint": "No action",
      "deleteConstraint": "No action"
    },
    {
      "id": "1468519dc0e0",
      "name": "fk_meta.attribute_package_id_core.package",
      "startTableId": "76898c7db092",
      "startFieldId": "25aacad20881",
      "endTableId": "2077a3dc4596",
      "endFieldId": "43f96212aca6",
      "cardinality": "many_to_one",
      "updateConstraint": "No action",
      "deleteConstraint": "No action"
    },
    {
      "id": "3017ef791654",
      "name": "fk_fact.daily_measure_fact_segment_id_core.segment",
      "startTableId": "05ea7bc82a14",
      "startFieldId": "8ed8e57782a2",
      "endTableId": "ec6e286ec1e3",
      "endFieldId": "ae5314c6a377",
      "cardinality": "many_to_one",
      "updateConstraint": "No action",
      "deleteConstraint": "No action"
    },
    {
      "id": "10709a028226",
      "name": "fk_fact.daily_measure_fact_item_id_core.segment",
      "startTableId": "05ea7bc82a14",
      "startFieldId": "73d25a8d37d2",
      "endTableId": "ec6e286ec1e3",
      "endFieldId": "29ed96142b36",
      "cardinality": "many_to_one",
      "updateConstraint": "No action",
      "deleteConstraint": "No action"
    },
    {
      "id": "9921c078911c",
      "name": "fk_fact.daily_measure_fact_location_node_id_core.segment",
      "startTableId": "05ea7bc82a14",
      "startFieldId": "2a0280450d52",
      "endTableId": "ec6e286ec1e3",
      "endFieldId": "593d350e8947",
      "cardinality": "many_to_one",
      "updateConstraint": "No action",
      "deleteConstraint": "No action"
    },
    {
      "id": "98edba1cc812",
      "name": "fk_fact.daily_measure_fact_attribute_id_meta.attribute",
      "startTableId": "05ea7bc82a14",
      "startFieldId": "a8f75c117533",
      "endTableId": "76898c7db092",
      "endFieldId": "3181e2ff3c43",
      "cardinality": "many_to_one",
      "updateConstraint": "No action",
      "deleteConstraint": "No action"
    },
    {
      "id": "73753f7bbca7",
      "name": "fk_fact.daily_measure_fact_scenario_id_core.scenario",
      "startTableId": "05ea7bc82a14",
      "startFieldId": "fa7c8f774f6a",
      "endTableId": "afe9774dbb38",
      "endFieldId": "bbef6c4f9dc3",
      "cardinality": "many_to_one",
      "updateConstraint": "No action",
      "deleteConstraint": "No action"
    },
    {
      "id": "a21fe269c2ea",
      "name": "fk_fact.daily_measure_fact_calc_version_id_core.calc_version",
      "startTableId": "05ea7bc82a14",
      "startFieldId": "19cc4a617ba0",
      "endTableId": "ddf9eb81b96b",
      "endFieldId": "335702703e9f",
      "cardinality": "many_to_one",
      "updateConstraint": "No action",
      "deleteConstraint": "No action"
    }
  ],
  "notes": [],
  "subjectAreas": [],
  "database": "postgresql",
  "types": [],
  "enums": [],
  "title": "Cleber ERD"
}